Metadata-Version: 2.1
Name: picot
Version: 0.1.0
Summary: Extract information from RSS feeds
Home-page: https://github.com/pybcn/picot
Author: Ignasi Fosch
Author-email: natx@y10k.ws
License: MIT
Platform: UNKNOWN
Classifier: License :: OSI Approved :: MIT License
Classifier: Programming Language :: Python :: 3
Classifier: Programming Language :: Python :: 3.6
Classifier: Programming Language :: Python :: 3.7
